{"title":"Combined feed","url":"https://ITCORD.github.io/event/all.xml","elements":[{"title":"컴포즈 정원사 (페스타 ─ 최신 밋업과 이벤트)","contents":"8월 31일 (토) · 오프라인","link":"https://festa.io/events/5701","retrieved":1722255162443},{"title":"구글 검색 엔진 최적화(테크니컬SEO) 집중 총정리 세미나 (페스타 ─ 최신 밋업과 이벤트)","contents":"8월 15일 (목) · 온라인","link":"https://festa.io/events/5702","retrieved":1722255162445},{"title":"[마감임박!] AI개발자로 성장하는 6개월, AI학교 아이펠 (페스타 ─ 최신 밋업과 이벤트)","contents":"8월 13일 (화) · 온라인","link":"https://festa.io/events/5700","retrieved":1722247700903},{"title":"유리 멘탈에서 다이아몬드 멘탈로 (페스타 ─ 최신 밋업과 이벤트)","contents":"7월 28일 (일) · 오프라인","link":"https://festa.io/events/5699","retrieved":1722240604723},{"title":"[새싹 금천 캠퍼스] 유니티 공인 자격증까지 1+1,XR 메타버스 창작자 실전 취업캠프 과정 (페스타 ─ 최신 밋업과 이벤트)","contents":"7월 29일 (월) · 오프라인","link":"https://festa.io/events/5698","retrieved":1722236898152},{"title":"부동산을 알려줘! (페스타 ─ 최신 밋업과 이벤트)","contents":"7월 28일 (일) · 오프라인","link":"https://festa.io/events/5631","retrieved":1722236898153},{"title":"실행의 힘 (페스타 ─ 최신 밋업과 이벤트)","contents":"7월 28일 (일) · 오프라인","link":"https://festa.io/events/5697","retrieved":1722226182342},{"title":"[유데미 X 웅진씽크빅 X 스나이퍼팩토리] 콘텐츠 디자인 인턴형 프로그램 과정 (페스타 ─ 최신 밋업과 이벤트)","contents":"9월 4일 (수) · 오프라인","link":"https://festa.io/events/5696","retrieved":1722220470626}]}