{"title":"Combined feed","url":"https://ITCORD.github.io/event/all.xml","elements":[{"title":"리얼리눅스: 리눅스 Zero 베이스 초보자 트러블 슈팅까지 (페스타 ─ 최신 밋업과 이벤트)","contents":"6월 25일 (화) · 온라인","link":"https://festa.io/events/5215","retrieved":1715051329549},{"title":"리얼리눅스: 리눅스 기초 쉘 스크립트 마스터 (페스타 ─ 최신 밋업과 이벤트)","contents":"6월 25일 (화) · 온라인","link":"https://festa.io/events/5214","retrieved":1715051329549},{"title":"리얼리눅스:리눅스 시스템 핵심 정리 (페스타 ─ 최신 밋업과 이벤트)","contents":"6월 25일 (화) · 온라인","link":"https://festa.io/events/5213","retrieved":1715051329551},{"title":"리얼리눅스:도커/쿠버네티스 단단한 기초 쌓기 (페스타 ─ 최신 밋업과 이벤트)","contents":"6월 25일 (화) · 온라인","link":"https://festa.io/events/5212","retrieved":1715051329553},{"title":"리얼리눅스:도커/K8s/클라우드(AWS) 네트워크 완전 정복 (페스타 ─ 최신 밋업과 이벤트)","contents":"6월 25일 (화) · 온라인","link":"https://festa.io/events/5211","retrieved":1715051329557},{"title":"리얼리눅스:서버엔지니어를 위한 트러블 슈팅 (페스타 ─ 최신 밋업과 이벤트)","contents":"6월 28일 (금) · 온라인","link":"https://festa.io/events/5210","retrieved":1715051329560},{"title":"[CJ올리브네트웍스] Cloudwave 3기 모집 (~5/30) (페스타 ─ 최신 밋업과 이벤트)","contents":"6월 24일 (월) · 오프라인","link":"https://festa.io/events/5209","retrieved":1715048717172},{"title":"[실시간 온라인] 데이터를 기반으로 기획하는 서비스 기획자, PM과정 (페스타 ─ 최신 밋업과 이벤트)","contents":"5월 7일 (화) · 온라인","link":"https://festa.io/events/5117","retrieved":1714993313776}]}