{"title":"페스타 ─ 최신 밋업과 이벤트","url":"https://festa.io/explore","favicon":"https://festa.io/public/ny/favicon/android-icon-192x192.png","elements":[{"title":"[Meet-up] 1st Datarize Dev","contents":"7월 24일 (수) · 오프라인","link":"https://festa.io/events/5588","retrieved":1720662995446},{"title":"프론트엔드 프로젝트 캠프 : 리액트 2기","contents":"7월 10일 (수) · 오프라인","link":"https://festa.io/events/5585","retrieved":1720662995446},{"title":"제20회 빅데이터 컨퍼런스","contents":"7월 27일 (토) · 오프라인","link":"https://festa.io/events/5581","retrieved":1720662995446},{"title":"K-디지털 트레이닝 국비지원 훈련생 모집","contents":"7월 10일 (수) · 오프라인","link":"https://festa.io/events/5580","retrieved":1720602441730},{"title":"판교 퇴근길 밋업 with 인프런 #05 백엔드 테스트코드","contents":"7월 24일 (수) · 오프라인","link":"https://festa.io/events/5576","retrieved":1720591809938},{"title":"파이토치 한국 사용자 모임 제3회 세미나","contents":"7월 20일 (토) · 오프라인","link":"https://festa.io/events/5578","retrieved":1720587921512},{"title":"게임페스티벌","contents":"7월 16일 (화) · 오프라인","link":"https://festa.io/events/5577","retrieved":1720519664726},{"title":"재테크 함께해요! : 1대1 클래스로 심도있게!","contents":"7월 21일 (일) · 오프라인","link":"https://festa.io/events/5566","retrieved":1720419029573}]}